model/__init__.py
roberta_base_en_plant_ner_case-0.1.3.dist-info/METADATA
roberta_base_en_plant_ner_case-0.1.3.dist-info/WHEEL
roberta_base_en_plant_ner_case-0.1.3.dist-info/top_level.txt
roberta_base_en_plant_ner_case-0.1.3.dist-info/RECORD
