Metadata-Version: 2.1
Name: roberta-base-en-plant-ner-case
Version: 0.1.3
Summary: A spaCy NER model for plant entities using RoBERTa
Home-page: https://github.com/yourusername/yourrepository
Author: Mohammad Othman
Classifier: Development Status :: 3 - Alpha
Classifier: Intended Audience :: Developers
Classifier: License :: OSI Approved :: Apache Software License
Classifier: Natural Language :: English
Classifier: Programming Language :: Python :: 3
Classifier: Programming Language :: Python :: 3.7
Classifier: Programming Language :: Python :: 3.8
Classifier: Programming Language :: Python :: 3.9
Requires-Python: >=3.7
Requires-Dist: spacy (>=3.0)
